mlflow_backend/__init__.py
mlflow_backend/model.py
mlflow_backend/models/__init__.py
mlflow_backend/models/mlflow_python_model.py
mlflow_backend/models/sentence_transformers_python_model.py
mlflow_backend/models/transformers_python_model.py
mlflow_backend_utils/__init__.py
mlflow_backend_utils/build_conda_env.sh
mlflow_backend_utils/build_triton_python_stub.sh
mlflow_backend_utils/cli.py
mlflow_backend_utils/conda_pack_utils.py
mlflow_backend_utils/constants.py
mlflow_backend_utils/sdk.py
mlflow_backend_utils/triton_stub_utils.py
mlflow_backend_utils/utils.py
mlflow_backend-1.1.0.dist-info/LICENSE
mlflow_backend-1.1.0.dist-info/METADATA
mlflow_backend-1.1.0.dist-info/WHEEL
mlflow_backend-1.1.0.dist-info/entry_points.txt
mlflow_backend-1.1.0.dist-info/RECORD
