Metadata-Version: 2.1
Name: mlflow_backend
Version: 1.1.0
Summary: Provides a tritonserver backend for running MLFlow models
Author: W.W. Grainger MLOps & Platform Team
Author-email: mlopsplatformteam@grainger.com
Requires-Python: >=3.10,<4.0
Classifier: Programming Language :: Python :: 3
Classifier: Programming Language :: Python :: 3.10
Classifier: Programming Language :: Python :: 3.11
Classifier: Programming Language :: Python :: 3.12
Classifier: Programming Language :: Python :: 3.13
Requires-Dist: boto3 (>=1.39.9,<2.0.0)
Requires-Dist: click (>=8.1.8,<9.0.0)
Requires-Dist: numpy (==1.*)
